cerberus/__init__.py
cerberus/aws_auth.py
cerberus/client.py
cerberus/network_util.py
cerberus/url_util.py
cerberus/user_auth.py
tests/matcher/__init__.py
tests/mocks/__init__.py
cerberus_python_client-2.5.4.dist-info/LICENSE.txt
cerberus_python_client-2.5.4.dist-info/METADATA
cerberus_python_client-2.5.4.dist-info/NOTICE
cerberus_python_client-2.5.4.dist-info/WHEEL
cerberus_python_client-2.5.4.dist-info/top_level.txt
cerberus_python_client-2.5.4.dist-info/RECORD
