Metadata-Version: 2.1
Name: cerberus-python-client
Version: 2.5.4
Summary: A python client for interacting with Cerberus
Home-page: https://github.com/Nike-Inc/cerberus-python-client
Author: Ann Wallace
Author-email: ann.wallace@nike.com
License: Apache License, v2.0
Keywords: cerberus nike
Platform: UNKNOWN
Requires-Dist: boto3
Requires-Dist: requests
